dothebackup/__init__.py
dothebackup/logger.py
dothebackup/plugins.py
dothebackup/runner.py
dothebackup/tools.py
dothebackup/types.py
dothebackup/ui.py
dothebackup/utils.py
dothebackup/plugs/borg.py
dothebackup/plugs/git.py
dothebackup/plugs/github.py
dothebackup/plugs/mysql.py
dothebackup/plugs/rsync.py
dothebackup/plugs/slapcat.py
dothebackup/plugs/tar.py
dothebackup-1.1.1.dist-info/DESCRIPTION.rst
dothebackup-1.1.1.dist-info/METADATA
dothebackup-1.1.1.dist-info/RECORD
dothebackup-1.1.1.dist-info/WHEEL
dothebackup-1.1.1.dist-info/entry_points.txt
dothebackup-1.1.1.dist-info/metadata.json
dothebackup-1.1.1.dist-info/top_level.txt
