Metadata-Version: 2.0
Name: dothebackup
Version: 1.1.1
Summary: backup tool with plugins
Home-page: https://github.com/xsteadfastx/DoTheBackup
Author: Marvin Steadfast
Author-email: marvin@xsteadfastx.org
License: MIT
Platform: ALL
Classifier: Programming Language :: Python :: 3
Classifier: Programming Language :: Python :: 3.3
Classifier: Programming Language :: Python :: 3.4
Classifier: Programming Language :: Python :: 3.5
Classifier: Programming Language :: Python :: 3 :: Only
Classifier: Development Status :: 3 - Alpha
Classifier: License :: OSI Approved :: MIT License
Classifier: Topic :: System :: Archiving :: Backup
Requires-Dist: Click (>=6.0.0)
Requires-Dist: pendulum (>=1.2.0)
Requires-Dist: pyyaml (>=3)
Requires-Dist: requests (>=2.0.0)
Requires-Dist: typing (>=3.6.0)
